drf_auth_email/__about__.py
drf_auth_email/__init__.py
drf_auth_email/abstracts.py
drf_auth_email/apps.py
drf_auth_email/checks.py
drf_auth_email/compat.py
drf_auth_email/email.py
drf_auth_email/emails.py
drf_auth_email/managers.py
drf_auth_email/models.py
drf_auth_email/schemas.py
drf_auth_email/serializers.py
drf_auth_email/settings.py
drf_auth_email/tests.py
drf_auth_email/typing.py
drf_auth_email/urls.py
drf_auth_email/utils.py
drf_auth_email/views.py
drf_auth_email/locale/ru/LC_MESSAGES/django.mo
drf_auth_email/migrations/0001_initial.py
drf_auth_email/migrations/__init__.py
drf_auth_email/templates/auth/email_change_new_confirm_email.html
drf_auth_email/templates/auth/email_change_new_confirm_email.txt
drf_auth_email/templates/auth/email_change_new_confirm_email_subject.txt
drf_auth_email/templates/auth/email_change_old_notify_email.html
drf_auth_email/templates/auth/email_change_old_notify_email.txt
drf_auth_email/templates/auth/email_change_old_notify_email_subject.txt
drf_auth_email/templates/auth/password_reset_email.html
drf_auth_email/templates/auth/password_reset_email.txt
drf_auth_email/templates/auth/password_reset_email_subject.txt
drf_auth_email/templates/auth/signup_email.html
drf_auth_email/templates/auth/signup_email.txt
drf_auth_email/templates/auth/signup_email_subject.txt
drf_auth_email/templates/auth/welcome_email.html
drf_auth_email/templates/auth/welcome_email.txt
drf_auth_email/templates/auth/welcome_email_subject.txt
drf_auth_email-0.0.5.dist-info/METADATA
drf_auth_email-0.0.5.dist-info/WHEEL
drf_auth_email-0.0.5.dist-info/licenses/LICENSE.txt
drf_auth_email-0.0.5.dist-info/RECORD
