Metadata-Version: 2.1
Name: drf-auth-email
Version: 0.0.5
Project-URL: Documentation, https://github.com/ArtyomYaprintsev/drf-auth-email#readme
Project-URL: Issues, https://github.com/ArtyomYaprintsev/drf-auth-email/issues
Project-URL: Source, https://github.com/ArtyomYaprintsev/drf-auth-email
Author-email: ArtyomYaprintsev <yapryntsev.a02@mail.ru>
License-Expression: MIT
License-File: LICENSE.txt
Classifier: Development Status :: 4 - Beta
Classifier: Programming Language :: Python
Classifier: Programming Language :: Python :: 3.8
Classifier: Programming Language :: Python :: 3.9
Classifier: Programming Language :: Python :: 3.10
Classifier: Programming Language :: Python :: 3.11
Classifier: Programming Language :: Python :: 3.12
Classifier: Programming Language :: Python :: Implementation :: CPython
Classifier: Programming Language :: Python :: Implementation :: PyPy
Requires-Python: >=3.8
Requires-Dist: django-ipware>=5.0
Requires-Dist: djangorestframework>=3.0
